oarepo_doi_generator/__init__.py
oarepo_doi_generator/api.py
oarepo_doi_generator/ext.py
oarepo_doi_generator/json_schema_mapping.py
oarepo_doi_generator/new_datasets_mapping.py
oarepo_doi_generator/version.py
oarepo_doi_generator/jsonschemas/__init__.py
oarepo_doi_generator/jsonschemas/datacite-oarepo-v1.0.0.json
oarepo_doi_generator-1.0.8.dist-info/LICENSE
oarepo_doi_generator-1.0.8.dist-info/METADATA
oarepo_doi_generator-1.0.8.dist-info/WHEEL
oarepo_doi_generator-1.0.8.dist-info/entry_points.txt
oarepo_doi_generator-1.0.8.dist-info/top_level.txt
oarepo_doi_generator-1.0.8.dist-info/RECORD
