Metadata-Version: 2.1
Name: oarepo-doi-generator
Version: 1.0.8
Summary: OARepo doi generator
Home-page: https://github.com/oarepo/oarepo-doi-generator
Author: Alzbeta Pokorna
Author-email: alzbeta.pokorna@cesnet.cz
License: MIT
Platform: any
Classifier: Environment :: Web Environment
Classifier: Intended Audience :: Developers
Classifier: License :: OSI Approved :: MIT License
Classifier: Operating System :: OS Independent
Classifier: Programming Language :: Python
Classifier: Topic :: Internet :: WWW/HTTP :: Dynamic Content
Classifier: Topic :: Software Development :: Libraries :: Python Modules
Classifier: Programming Language :: Python :: 2
Classifier: Programming Language :: Python :: 2.7
Classifier: Programming Language :: Python :: 3
Classifier: Programming Language :: Python :: 3.5
Classifier: Development Status :: 4 - Beta
License-File: LICENSE
Requires-Dist: deepmerge
Provides-Extra: tests
Requires-Dist: oarepo[tests] (~=3.3.40) ; extra == 'tests'
Requires-Dist: marshmallow-utils ; extra == 'tests'
Requires-Dist: responses ; extra == 'tests'
Requires-Dist: oarepo-validate ; extra == 'tests'
Requires-Dist: oarepo-communities ; extra == 'tests'
Requires-Dist: deepmerge ; extra == 'tests'
Requires-Dist: oarepo-invenio-model ; extra == 'tests'
